mdchunk/__init__.py
mdchunk/py.typed
mdchunk-0.1.0.dist-info/METADATA
mdchunk-0.1.0.dist-info/WHEEL
mdchunk-0.1.0.dist-info/RECORD
