Metadata-Version: 2.4
Name: mdchunk
Version: 0.1.0
Summary: Markdown-aware text chunking library
Author-email: Kaan Giray Buzluk <kaangiray26@protonmail.com>
Requires-Python: >=3.12
